apiverve_domainexpiration/__init__.py
apiverve_domainexpiration/apiClient.py
apiverve_domainexpiration/exceptions.py
apiverve_domainexpiration/setup.py
apiverve_domainexpiration/setup_dep.py
apiverve_domainexpiration/tests/__init__.py
apiverve_domainexpiration/tests/test_api.py
apiverve_domainexpiration-1.1.7.dist-info/LICENSE
apiverve_domainexpiration-1.1.7.dist-info/METADATA
apiverve_domainexpiration-1.1.7.dist-info/WHEEL
apiverve_domainexpiration-1.1.7.dist-info/top_level.txt
apiverve_domainexpiration-1.1.7.dist-info/RECORD
